dividebyzero/__init__.py
dividebyzero/array.py
dividebyzero/exceptions.py
dividebyzero/fft.py
dividebyzero/linalg.py
dividebyzero/numpy_compat.py
dividebyzero/numpy_registry.py
dividebyzero/operators.py
dividebyzero/random.py
dividebyzero/registry.py
dividebyzero/quantum/__init__.py
dividebyzero/quantum/gauge.py
dividebyzero/quantum/gauge_groups.py
dividebyzero/quantum/holonomy.py
dividebyzero/quantum/tensor.py
dividebyzero-0.1.3.dist-info/METADATA
dividebyzero-0.1.3.dist-info/WHEEL
dividebyzero-0.1.3.dist-info/RECORD
