Metadata-Version: 2.4
Name: dividebyzero
Version: 0.1.3
Summary: A NumPy extension implementing division by zero as dimensional reduction
Author-email: Your Name <your.email@example.com>
License-Expression: MIT
Keywords: mathematics,numpy,quantum,tensor
Classifier: Development Status :: 4 - Beta
Classifier: Intended Audience :: Science/Research
Classifier: License :: OSI Approved :: MIT License
Classifier: Programming Language :: Python :: 3
Classifier: Topic :: Scientific/Engineering :: Mathematics
Requires-Python: >=3.8
Requires-Dist: numpy>=1.20.0
Requires-Dist: scipy>=1.7.0
Provides-Extra: quantum
Requires-Dist: networkx>=2.6.0; extra == 'quantum'
Provides-Extra: test
Requires-Dist: pytest-cov>=2.0; extra == 'test'
Requires-Dist: pytest>=6.0; extra == 'test'
